CHANGES.txt
README.txt
setup.py
src/docs/HISTORY.txt
src/docs/INSTALL.txt
src/docs/LICENSE.GPL
src/docs/LICENSE.txt
src/getpaid/__init__.py
src/getpaid.formgen.egg-info/PKG-INFO
src/getpaid.formgen.egg-info/SOURCES.txt
src/getpaid.formgen.egg-info/dependency_links.txt
src/getpaid.formgen.egg-info/entry_points.txt
src/getpaid.formgen.egg-info/namespace_packages.txt
src/getpaid.formgen.egg-info/not-zip-safe
src/getpaid.formgen.egg-info/requires.txt
src/getpaid.formgen.egg-info/top_level.txt
src/getpaid/formgen/__init__.py
src/getpaid/formgen/config.py
src/getpaid/formgen/configure.zcml
src/getpaid/formgen/interfaces.py
src/getpaid/formgen/Extensions/Install.py
src/getpaid/formgen/Extensions/__init__.py
src/getpaid/formgen/browser/__init__.py
src/getpaid/formgen/browser/configure.zcml
src/getpaid/formgen/content/__init__.py
src/getpaid/formgen/content/checkout.py
src/getpaid/formgen/content/configure.zcml
src/getpaid/formgen/content/getpaidFormMailerAdapter.py
src/getpaid/formgen/content/getpaidpfgadapter.py
src/getpaid/formgen/portlets/__init__.py
src/getpaid/formgen/portlets/configure.zcml
src/getpaid/formgen/profiles/default/factorytool.xml
src/getpaid/formgen/profiles/default/metadata.xml
src/getpaid/formgen/profiles/default/portlets.xml
src/getpaid/formgen/profiles/default/rolemap.xml
src/getpaid/formgen/profiles/default/types.xml
src/getpaid/formgen/profiles/default/types/GetPaidFormMailerAdapter.xml
src/getpaid/formgen/profiles/default/types/GetpaidPFGAdapter.xml
src/getpaid/formgen/tests/__init__.py
src/getpaid/formgen/tests/test_functional.py
src/getpaid/formgen/tests/test_functional_oneshot_success.txt