Metadata-Version: 1.0
Name: getpaid.formgen
Version: 0.6
Summary: PloneGetPaid-PloneFormGen integration
Home-page: http://dingoskidneys.com/cgi-bin/hgwebdir.cgi/getpaid.formgen
Author: Daniel Holth
Author-email: daniel.holth@exac.com
License: UNKNOWN
Keywords: plone plonegetpaid ploneformgen
Platform: UNKNOWN
Classifier: Framework :: Plone
Classifier: Programming Language :: Python
Classifier: Topic :: Software Development :: Libraries :: Python Modules
Classifier: License :: OSI Approved :: GNU General Public License (GPL)
